dtk_api/__init__.py
dtk_api/api_async.py
dtk_api/api_std.py
dtk_api/api_sync.py
dtk_api/base.py
dtk_api/dt_resp.py
dtk_api/dt_resp_v2.py
dtk_api/gen.py
dtk_api/test_demo.py
dtk_api/test_dtk.py
dtk_api/test_gen.py
dtk_api/test_shared.py
dtk_api/test_std.py
dtk_api/test_type.py
dtk_api/test_value.py
dtk_api-0.7.1.dist-info/WHEEL
dtk_api-0.7.1.dist-info/METADATA
dtk_api-0.7.1.dist-info/RECORD
