Metadata-Version: 2.1
Name: dtk-api
Version: 0.7.1
Summary: 大淘客接口
Author: dev
Author-email: dev@qiyutech.tech
Requires-Python: >=3.9,<4.0
Classifier: Programming Language :: Python :: 3
Classifier: Programming Language :: Python :: 3.9
Requires-Dist: aiohttp (>=3.7,<4)
Requires-Dist: pydantic (>=1.7,<2)
Requires-Dist: requests (>=2.24,<3)
Requires-Dist: tbk_api (>=0.2.1,<0.3)
